LICENSE
LICENSE.txt
MANIFEST.in
README.md
backup2s3-sample.yml
requirements.txt
setup.py
backup2s3/__init__.py
backup2s3.egg-info/PKG-INFO
backup2s3.egg-info/SOURCES.txt
backup2s3.egg-info/dependency_links.txt
backup2s3.egg-info/requires.txt
backup2s3.egg-info/top_level.txt
bin/backup2s3