Metadata-Version: 1.1
Name: backup2s3
Version: 0.1
Summary: Backup files and mysql to AWS S3
Home-page: https://github.com/wavedocs/backup2s3
Author: Nazar Suryev
Author-email: wavedocs@gmail.com
License: GPLv3
Download-URL: https://github.com/wavedocs/backup2s3/archive/0.1.tar.gz
Keywords: backup,s3,mysql
Platform: UNKNOWN
Classifier: Development Status :: 5 - Production/Stable
Classifier: Topic :: System :: Archiving :: Backup
Classifier: License :: OSI Approved :: MIT License
Classifier: Programming Language :: Python :: 3.5
Classifier: Programming Language :: Python :: 3.6
